perdream_weather_mcp/__init__.py
perdream_weather_mcp-0.1.2.dist-info/WHEEL
perdream_weather_mcp-0.1.2.dist-info/entry_points.txt
perdream_weather_mcp-0.1.2.dist-info/METADATA
perdream_weather_mcp-0.1.2.dist-info/RECORD
